tpclean/Wrappers.py
tpclean/__init__.py
tpclean/tpclean.py
tpclean-0.6.8.4.dist-info/LICENSE
tpclean-0.6.8.4.dist-info/METADATA
tpclean-0.6.8.4.dist-info/WHEEL
tpclean-0.6.8.4.dist-info/top_level.txt
tpclean-0.6.8.4.dist-info/RECORD
